README.md
setup.cfg
setup.py
prune/__init__.py
prune.egg-info/PKG-INFO
prune.egg-info/SOURCES.txt
prune.egg-info/dependency_links.txt
prune.egg-info/top_level.txt