Metadata-Version: 2.1
Name: prune
Version: 0.0.1
Summary: Trim Entries from a Python Dictionary
Home-page: https://github.com/DanielJDufour/prune
Author: Daniel J. Dufour
Author-email: daniel.j.dufour@gmail.com
License: UNKNOWN
Download-URL: https://github.com/DanielJDufour/prune/tarball/download
Keywords: branch,dictionary,entry,prune,python,string,unpick
Platform: UNKNOWN
Classifier: Development Status :: 5 - Production/Stable
Classifier: Programming Language :: Python :: 3
Classifier: License :: CC0 1.0 Universal (CC0 1.0) Public Domain Dedication
Classifier: Operating System :: OS Independent
